<design_size title="Design Size Report">
    <item name="Total Instructions per Compilation Phase">
        <table>
            <keys size="4">Phase, Step, Instructions, Description</keys>
            <column name="Compile/Link">,  14469, After all functions are compiled and linked into a single design</column>
            <column name="">, , </column>
            <column name="Unroll/Inline">, , After user unroll and inline pragmas are applied</column>
            <column name="">(1) unroll, 203028 *, user unroll pragmas are applied</column>
            <column name="">(2) simplification, 115767 *, simplification of applied user unroll pragmas</column>
            <column name="">(3) inline, 111999 *, user inline pragmas are applied</column>
            <column name="">(4) simplification, 102647 *, simplification of applied user inline pragmas</column>
            <column name="">, , </column>
            <column name="Array/Struct">, , After user array partition and struct aggregate/disaggregate pragmas are applied</column>
            <column name="">(1) array partition, 102664 *, user array partition pragmas are applied</column>
            <column name="">(2) simplification, 102644 *, simplification of applied user array partition &amp; struct aggregate/disaggregate pragmas</column>
            <column name="">(3) aggregate/disaggregate, 102656 *, user struct aggregate/disaggregate pragmas are applied</column>
            <column name="">(4) array reshape, 102674 *, apply array reshape pragmas</column>
            <column name="">(5) access patterns, 102676 *, array access pattern optmizations</column>
            <column name="">, , </column>
            <column name="Performance">, , After transformations are applied to meet performance pragma targets</column>
            <column name="">(1) loop simplification, 102640 *, loop and instruction simplification</column>
            <column name="">(2) parallelization, 102638 *, loops are unrolled or pipelined to meet performance targets</column>
            <column name="">(3) array partition, 113341 *, arrays are partitioned to meet performance targets</column>
            <column name="">(4) simplification, 104000 *, simplification of design after performance transformations</column>
            <column name="">, , </column>
            <column name="HW Transforms">, , After hardware transfomations</column>
            <column name="">(1) lowering, 104014 *, initial conversion to HW specific instructions</column>
            <column name="">(2) optimizations, 104069 *, high level synthesis optimizations</column>
        </table>
    </item>
    <item name="Instructions per Function for each Compilation Phase">
        <hiertable>
            <header size="7" col0="Function" col1="Location" col2="Compile/Link" col3="Unroll/Inline" col4="Array/Struct" col5="Performance" col6="HW Transforms"/>
            <rows>
                <row id="0" col0="cnn_gesture_top" col1="cnn_gesture_hls.cpp:215" col2="14469" col3="102647" col3_note="*" col4="102676" col4_note="*" col5="104000" col5_note="*" col6="104069" col6_note="*">
                    <row id="3" col0="conv1_block" col1="cnn_gesture_hls.cpp:33" col2="5141" col3="" col4="" col5="" col6="">
                        <row id="14" col0="conv_index" col1="cnn_gesture_hls.cpp:24" col2="5" col3="" col4="" col5="" col6=""/>
                        <row id="5" col0="relu" col1="cnn_gesture_hls.cpp:18" col2="148" col3="" col4="" col5="" col6=""/>
                        <row id="13" col0="sqrt" col1="sqrtfloat.cpp:6" col2="2" col3="" col4="" col5="" col6=""/>
                    </row>
                    <row id="6" col0="maxpool1" col1="cnn_gesture_hls.cpp:72" col2="67" col3="" col4="" col5="" col6=""/>
                    <row id="1" col0="conv2_block" col1="cnn_gesture_hls.cpp:88" col2="5141" col3="" col4="" col5="" col6="">
                        <row id="14" col0="conv_index" col1="cnn_gesture_hls.cpp:24" col2="5" col3="" col4="" col5="" col6=""/>
                        <row id="5" col0="relu" col1="cnn_gesture_hls.cpp:18" col2="148" col3="" col4="" col5="" col6=""/>
                        <row id="13" col0="sqrt" col1="sqrtfloat.cpp:6" col2="2" col3="" col4="" col5="" col6=""/>
                    </row>
                    <row id="9" col0="maxpool2" col1="cnn_gesture_hls.cpp:123" col2="67" col3="" col4="" col5="" col6=""/>
                    <row id="4" col0="flatten" col1="cnn_gesture_hls.cpp:139" col2="30" col3="" col4="" col5="" col6=""/>
                    <row id="11" col0="dense1" col1="cnn_gesture_hls.cpp:154" col2="1463" col3="" col4="" col5="" col6="">
                        <row id="7" col0="dense_index" col1="cnn_gesture_hls.cpp:29" col2="3" col3="" col4="" col5="" col6=""/>
                        <row id="5" col0="relu" col1="cnn_gesture_hls.cpp:18" col2="148" col3="" col4="" col5="" col6=""/>
                    </row>
                    <row id="10" col0="dense2_logits" col1="cnn_gesture_hls.cpp:175" col2="1313" col3="" col4="" col5="" col6="">
                        <row id="7" col0="dense_index" col1="cnn_gesture_hls.cpp:29" col2="3" col3="" col4="" col5="" col6=""/>
                    </row>
                    <row id="2" col0="softmax" col1="cnn_gesture_hls.cpp:194" col2="1185" col3="" col4="" col5="" col6="">
                        <row id="8" col0="exp" col1="expfloat.cpp:15" col2="4" col3="" col4="" col5="" col6="">
                            <row id="12" col0="exp" col1="hls_exp_float.cpp:15" col2="2" col3="" col4="" col5="" col6=""/>
                        </row>
                    </row>
                    <row id="14" col0="conv_index" col1="cnn_gesture_hls.cpp:24" col2="" col3="570" col3_disp="   570 (114 calls)" col4="570" col4_disp="   570 (114 calls)" col5="570" col5_disp="   570 (114 calls)" col6="570" col6_disp="   570 (114 calls)"/>
                    <row id="7" col0="dense_index" col1="cnn_gesture_hls.cpp:29" col2="" col3="5184" col3_disp=" 5,184 (1728 calls)" col4="5184" col4_disp=" 5,184 (1728 calls)" col5="5184" col5_disp=" 5,184 (1728 calls)" col6="5184" col6_disp=" 5,184 (1728 calls)"/>
                </row>
            </rows>
            <notes>
                <note name="*" desc="Exceeded design size warning message threshold"/>
            </notes>
        </hiertable>
    </item>
    <item name="Design Size Message Settings">
        <table>
            <keys size="3">Message Setting, Value, Description</keys>
            <column name="config_compile -design_size_maximum_warning">100000, Show a warning when total design instructions exceeds this value</column>
        </table>
    </item>
</design_size>
